[
    {
      "title": "title 10",
      "imageurl": "https://images.pexels.com/photos/3532557/pexels-photo-3532557.jpeg?auto=compress&cs=tinysrgb&dpr=1&w=500"
    },
    {
      "title": "title 2",
      "imageurl": "https://images.pexels.com/photos/3532544/pexels-photo-3532544.jpeg?auto=compress&cs=tinysrgb&dpr=1&w=500"
    },
    {
      "title": "title 3",
      "imageurl": "https://images.pexels.com/photos/2522663/pexels-photo-2522663.jpeg?auto=compress&cs=tinysrgb&dpr=1&w=500"
    }
  ]
  